Products.TemporaryFolder-7.0-py3.11-nspkg.pth
Products/TemporaryFolder/TemporaryFolder.py
Products/TemporaryFolder/__init__.py
Products/TemporaryFolder/mount.py
Products/TemporaryFolder/dtml/addTemporaryFolder.dtml
Products/TemporaryFolder/dtml/mountfail.dtml
Products/TemporaryFolder/tests/__init__.py
Products/TemporaryFolder/tests/testTemporaryFolder.py
Products/TemporaryFolder/tests/test_mount.py
Products.TemporaryFolder-7.0.dist-info/LICENSE.txt
Products.TemporaryFolder-7.0.dist-info/METADATA
Products.TemporaryFolder-7.0.dist-info/WHEEL
Products.TemporaryFolder-7.0.dist-info/entry_points.txt
Products.TemporaryFolder-7.0.dist-info/namespace_packages.txt
Products.TemporaryFolder-7.0.dist-info/top_level.txt
Products.TemporaryFolder-7.0.dist-info/RECORD
